exo/API.py
exo/API_cursors.py
exo/API_scheduling.py
exo/API_types.py
exo/__init__.py
exo/main.py
exo/backend/LoopIR_compiler.py
exo/backend/__init__.py
exo/backend/mem_analysis.py
exo/backend/parallel_analysis.py
exo/backend/prec_analysis.py
exo/backend/win_analysis.py
exo/core/LoopIR.py
exo/core/LoopIR_pprint.py
exo/core/__init__.py
exo/core/configs.py
exo/core/extern.py
exo/core/internal_cursors.py
exo/core/memory.py
exo/core/prelude.py
exo/core/proc_eqv.py
exo/frontend/__init__.py
exo/frontend/boundscheck.py
exo/frontend/parse_fragment.py
exo/frontend/pattern_match.py
exo/frontend/pyparser.py
exo/frontend/syntax.py
exo/frontend/typecheck.py
exo/libs/__init__.py
exo/libs/custom_malloc.c
exo/libs/custom_malloc.h
exo/libs/externs.py
exo/libs/gemm_acc_malloc.c
exo/libs/gemm_acc_malloc.h
exo/libs/gemm_malloc.c
exo/libs/gemm_malloc.h
exo/libs/memories.py
exo/platforms/__init__.py
exo/platforms/gemmini.py
exo/platforms/neon.py
exo/platforms/rvv.py
exo/platforms/x86.py
exo/rewrite/LoopIR_scheduling.py
exo/rewrite/LoopIR_unification.py
exo/rewrite/__init__.py
exo/rewrite/analysis_simplify.py
exo/rewrite/new_analysis_core.py
exo/rewrite/new_eff.py
exo/rewrite/range_analysis.py
exo/stdlib/__init__.py
exo/stdlib/analysis.py
exo/stdlib/halide_scheduling_ops.py
exo/stdlib/higher_order.py
exo/stdlib/inspection.py
exo/stdlib/range_analysis.py
exo/stdlib/rc_wrappers.py
exo/stdlib/scheduling.py
exo/stdlib/stdlib.py
exo_lang-1.0.0.data/data/share/exo/cmake/AddExoLibrary.cmake
exo_lang-1.0.0.data/data/share/exo/cmake/ExoConfig.cmake
exo_lang-1.0.0.data/data/share/exo/cmake/ExoConfigVersion.cmake
exo_lang-1.0.0.dist-info/LICENSE.md
exo_lang-1.0.0.dist-info/METADATA
exo_lang-1.0.0.dist-info/WHEEL
exo_lang-1.0.0.dist-info/entry_points.txt
exo_lang-1.0.0.dist-info/top_level.txt
exo_lang-1.0.0.dist-info/RECORD
