Metadata-Version: 2.1
Name: exo-lang
Version: 1.0.0
Summary: Exo: Exocompiled Array Language
Home-page: https://exo-lang.dev/
Maintainer: Yuka Ikarashi
Maintainer-email: yuka@csail.mit.edu
License: MIT License
Keywords: exo,exocompilation,array,dsl,language,performance
Classifier: Development Status :: 3 - Alpha
Classifier: License :: OSI Approved :: MIT License
Classifier: Intended Audience :: Developers
Classifier: Intended Audience :: Science/Research
Classifier: Operating System :: OS Independent
Classifier: Programming Language :: C
Classifier: Programming Language :: Python :: 3
Classifier: Programming Language :: Python :: 3 :: Only
Classifier: Programming Language :: Python :: 3.9
Classifier: Programming Language :: Python :: 3.10
Classifier: Topic :: Scientific/Engineering
Classifier: Topic :: Scientific/Engineering :: Artificial Intelligence
Classifier: Topic :: Scientific/Engineering :: Image Processing
Classifier: Topic :: Software Development
Classifier: Topic :: Software Development :: Code Generators
Classifier: Topic :: Software Development :: Compilers
License-File: LICENSE.md
Requires-Dist: PySMT>=0.9.5
Requires-Dist: asdl-adt<0.2,>=0.1
Requires-Dist: asdl>=0.1.5
Requires-Dist: build>=1.2.1
Requires-Dist: z3-solver>=4.13.0.0
Requires-Dist: yapf>=0.40.2
